{
  "project_info": {
    "project_number": "1044864992324",
    "project_id": "testsparshapp",
    "storage_bucket": "testsparshapp.appspot.com"
  },
  "client": [
    {
      "client_info": {
        "mobilesdk_app_id": "1:1044864992324:android:e348c8815a2ed348a3a811",
        "android_client_info": {
          "package_name": "com.sparsh.app"
        }
      },
      "oauth_client": [
        {
          "client_id": "1044864992324-nvts353be6j0987o1g076efukklh2dj0.apps.googleusercontent.com",
          "client_type": 3
        }
      ],
      "api_key": [
        {
          "current_key": "AIzaSyBk4ikB443V_Bwju8OmwEKlIxcPpLKqOZ4"
        }
      ],
      "services": {
        "appinvite_service": {
          "other_platform_oauth_client": [
            {
              "client_id": "1044864992324-nvts353be6j0987o1g076efukklh2dj0.apps.googleusercontent.com",
              "client_type": 3
            }
          ]
        }
      }
    }
  ],
  "configuration_version": "1"
}